LICENSE
MANIFEST.in
README.md
VERSION
setup.cfg
setup.py
src/__init__.py
src/iupac.py
src/libssw.py
src/sswobj.py
src/ssw/ssw.c
src/ssw/ssw.h
ssw.egg-info/PKG-INFO
ssw.egg-info/SOURCES.txt
ssw.egg-info/dependency_links.txt
ssw.egg-info/not-zip-safe
ssw.egg-info/requires.txt
ssw.egg-info/top_level.txt