Metadata-Version: 2.1
Name: ssw
Version: 0.4.1
Summary: Smith-Waterman Sequence Aligner
Home-page: https://github.com/vishnubob/ssw
Author: Giles Hall
Author-email: giles@polymerase.org
License: UNKNOWN
Download-URL: https://github.com/vishnubob/ssw/archive/v0.4.1.tar.gz
Keywords: bioinformatics,sequence alignment,smith-waterman,genomics,proteomics
Platform: any
Classifier: Development Status :: 5 - Production/Stable
Classifier: Programming Language :: Python
Classifier: Programming Language :: Python :: 2
Classifier: Programming Language :: Python :: 2.7
Classifier: Programming Language :: Python :: 3
Classifier: Programming Language :: Python :: 3.3
Classifier: Programming Language :: Python :: 3.4
Classifier: Programming Language :: Python :: 3.5
Classifier: Programming Language :: Python :: 3.6
Classifier: Programming Language :: Python :: 3.7
Classifier: License :: OSI Approved :: MIT License
Classifier: Intended Audience :: Science/Research
Classifier: Topic :: Scientific/Engineering :: Bio-Informatics
